gym_socks/__init__.py
gym_socks/algorithms/__init__.py
gym_socks/algorithms/base.py
gym_socks/algorithms/kernel.py
gym_socks/algorithms/control/__init__.py
gym_socks/algorithms/control/common.py
gym_socks/algorithms/control/kernel_control_bwd.py
gym_socks/algorithms/control/kernel_control_fwd.py
gym_socks/algorithms/control/tests/__init__.py
gym_socks/algorithms/identification/__init__.py
gym_socks/algorithms/identification/kernel_linear_id.py
gym_socks/algorithms/identification/tests/__init__.py
gym_socks/algorithms/identification/tests/test_kernel_linear_id.py
gym_socks/algorithms/reach/__init__.py
gym_socks/algorithms/reach/common.py
gym_socks/algorithms/reach/kernel_sr.py
gym_socks/algorithms/reach/kernel_sr_max.py
gym_socks/algorithms/reach/monte_carlo.py
gym_socks/algorithms/reach/separating_kernel.py
gym_socks/algorithms/reach/tests/__init__.py
gym_socks/algorithms/reach/tests/test_monte_carlo.py
gym_socks/envs/QUAD20.py
gym_socks/envs/__init__.py
gym_socks/envs/core.py
gym_socks/envs/cwh.py
gym_socks/envs/dynamical_system.py
gym_socks/envs/integrator.py
gym_socks/envs/nonholonomic.py
gym_socks/envs/obstacle.py
gym_socks/envs/planar_quad.py
gym_socks/envs/point_mass.py
gym_socks/envs/tora.py
gym_socks/envs/world.py
gym_socks/envs/tests/__init__.py
gym_socks/envs/tests/test_core.py
gym_socks/envs/tests/test_cwh.py
gym_socks/envs/tests/test_envs.py
gym_socks/envs/tests/test_integrator.py
gym_socks/envs/tests/test_nonholonomic.py
gym_socks/envs/tests/test_tora.py
gym_socks/envs/tests/test_world.py
gym_socks/kernel/__init__.py
gym_socks/kernel/metrics.py
gym_socks/kernel/probability.py
gym_socks/kernel/tests/__init__.py
gym_socks/kernel/tests/test_kernel.py
gym_socks/policies/__init__.py
gym_socks/policies/policy.py
gym_socks/policies/tests/__init__.py
gym_socks/policies/tests/test_policy.py
gym_socks/sampling/__init__.py
gym_socks/sampling/sample.py
gym_socks/sampling/transform.py
gym_socks/sampling/tests/__init__.py
gym_socks/sampling/tests/test_sample.py
gym_socks-0.1.0a1.dist-info/LICENSE
gym_socks-0.1.0a1.dist-info/METADATA
gym_socks-0.1.0a1.dist-info/WHEEL
gym_socks-0.1.0a1.dist-info/top_level.txt
gym_socks-0.1.0a1.dist-info/RECORD
