Metadata-Version: 2.1
Name: gym-socks
Version: 0.1.0a1
Summary: SOCKS: Stochastic Optimal Control using Kernel Methods
Home-page: https://github.com/ajthor/socks
Author: Adam Thorpe
Author-email: ajthor@unm.edu
License: UNKNOWN
Platform: UNKNOWN
Classifier: Programming Language :: Python :: 3
Classifier: License :: OSI Approved :: MIT License
Classifier: Operating System :: OS Independent
Requires-Python: >=3.7
License-File: LICENSE
Requires-Dist: gym (>=0.18)
Requires-Dist: matplotlib (>=3.4)
Requires-Dist: numpy (>=1.18.0)
Requires-Dist: pyglet (>=1.4.0)
Requires-Dist: pyyaml (>=6.0)
Requires-Dist: sacred (>=0.8.2)
Requires-Dist: scikit-learn (>=1.0)
Requires-Dist: scipy (>=1.4.1)
Requires-Dist: tqdm (>=4.62.3)
